dlc2kinematics/__init__.py
dlc2kinematics/version.py
kinematik/__init__.py
kinematik/version.py
kinematik-0.0b1.dist-info/METADATA
kinematik-0.0b1.dist-info/WHEEL
kinematik-0.0b1.dist-info/top_level.txt
kinematik-0.0b1.dist-info/RECORD
